todoms/__init__.py
todoms/attributes.py
todoms/client.py
todoms/convertable.py
todoms/filters.py
todoms/resources.py
todoms/converters/__init__.py
todoms/converters/basic.py
todoms/converters/recurrence.py
todoms/fields/__init__.py
todoms/fields/basic.py
todoms/fields/recurrence.py
todoms/provider/__init__.py
todoms/provider/base.py
todoms/provider/browser_provider.py
todoms/recurrence/__init__.py
todoms/recurrence/patterns.py
todoms/recurrence/ranges.py
todo_ms_client-0.1.0.dist-info/LICENSE
todo_ms_client-0.1.0.dist-info/METADATA
todo_ms_client-0.1.0.dist-info/WHEEL
todo_ms_client-0.1.0.dist-info/top_level.txt
todo_ms_client-0.1.0.dist-info/RECORD
