Metadata-Version: 2.1
Name: todo-ms-client
Version: 0.1.0
Summary: Unofficial Python library for MS ToDo API
Home-page: https://github.com/kam193/todo-ms-client
Author: Kamil Mańkowski
Author-email: gh.welcome@tools.kam193.eu
License: MIT
Classifier: Development Status :: 3 - Alpha
Classifier: License :: OSI Approved :: MIT License
Classifier: Programming Language :: Python :: 3
Classifier: Programming Language :: Python :: 3.9
Classifier: Programming Language :: Python :: 3.10
Requires-Python: >=3.9
License-File: LICENSE
Requires-Dist: requests (>=2.23.0)
Requires-Dist: requests-oauthlib (>=1.3.0)
Requires-Dist: python-dateutil (>=2.8.1)
Requires-Dist: furl (>=2.1.0)
